setup.py
src/polkadot/__init__.py
src/polkadot/dance.py
src/polkadot/globber.py
src/polkadot/loader.py
src/polkadot/logging.py
src/polkadot/operations.py
src/polkadot.egg-info/PKG-INFO
src/polkadot.egg-info/SOURCES.txt
src/polkadot.egg-info/dependency_links.txt
src/polkadot.egg-info/not-zip-safe
src/polkadot.egg-info/requires.txt
src/polkadot.egg-info/top_level.txt