Metadata-Version: 1.0
Name: polkadot
Version: 1.0.0
Summary: Python dotfiles manager
Home-page: https://github.com/brian-l/polkadot
Author: Brian Lee
Author-email: brian-l@users.noreply.github.com
License: MIT
Platform: UNKNOWN
